lococore/__init__.py
lococore/core.py
lococore/py.typed
lococore-0.2.0.dist-info/LICENSE
lococore-0.2.0.dist-info/METADATA
lococore-0.2.0.dist-info/WHEEL
lococore-0.2.0.dist-info/RECORD
