Metadata-Version: 2.1
Name: lococore
Version: 0.2.0
Summary: LocoCore is a library that provides a base class for multilingual applications.
Home-page: https://github.com/drago-suzuki58/LocoCore
License: MIT
Keywords: json,localization,translation,localisation,multi-language
Author: drago-suzuki58
Author-email: dorasuzu58@gmail.com
Requires-Python: >=3.11,<4.0
Classifier: License :: OSI Approved :: MIT License
Classifier: Programming Language :: Python :: 3
Classifier: Programming Language :: Python :: 3.11
Classifier: Programming Language :: Python :: 3.12
Project-URL: Issues, https://github.com/drago-suzuki58/LocoCore/issues
Project-URL: Repository, https://github.com/drago-suzuki58/LocoCore
